Metadata-Version: 2.1
Name: odoo-addon-account_fiscal_position_partner_type
Version: 18.0.1.1.0
Requires-Python: >=3.10
Requires-Dist: odoo==18.0.*
Summary: Account Fiscal Position Partner Type
Home-page: https://github.com/OCA/account-fiscal-rule
License: AGPL-3
Author: Sygel Technology,Odoo Community Association (OCA)
Author-email: support@odoo-community.org
Classifier: Programming Language :: Python
Classifier: Framework :: Odoo
Classifier: Framework :: Odoo :: 18.0
Classifier: License :: OSI Approved :: GNU Affero General Public License v3
Classifier: Development Status :: 5 - Production/Stable
